LICENSE
MANIFEST.in
README.md
setup.py
aerforge/__init__.py
aerforge/animation.py
aerforge/build.py
aerforge/color.py
aerforge/entity.py
aerforge/error.py
aerforge/input.py
aerforge/line.py
aerforge/logo.py
aerforge/main.py
aerforge/math.py
aerforge/mixer.py
aerforge/polygon.py
aerforge/shape.py
aerforge/sprite.py
aerforge/text.py
aerforge.egg-info/PKG-INFO
aerforge.egg-info/SOURCES.txt
aerforge.egg-info/dependency_links.txt
aerforge.egg-info/requires.txt
aerforge.egg-info/top_level.txt
aerforge/assets/icon/icon.png
aerforge/assets/icon/icon_ico.ico
aerforge/assets/icon/icon_white.png
aerforge/assets/logo/logo.png
aerforge/prefabs/__init__.py
aerforge/prefabs/button.py
aerforge/prefabs/camera.py
aerforge/prefabs/cursor.py
aerforge/prefabs/exit_button.py
aerforge/prefabs/fps_counter.py
aerforge/prefabs/gravity.py
aerforge/prefabs/gun.py
aerforge/prefabs/particle.py
aerforge/prefabs/platformer_controller.py
aerforge/prefabs/renderer_3d.py
aerforge/prefabs/textbox.py
aerforge/prefabs/top_view_controller.py
aerforge/scripts/__init__.py
aerforge/scripts/double_click_handler.py
aerforge/scripts/draggable.py
aerforge/scripts/follow.py
aerforge/scripts/follow_camera.py
aerforge/scripts/gravity.py
aerforge/scripts/modifiable.py
aerforge/scripts/smooth_follow.py
aerforge/scripts/smooth_follow_camera.py
aerforge/scripts/tooltip.py