Metadata-Version: 2.1
Name: aerforge
Version: 0.3.5
Summary: A game engine made with pygame.
Home-page: https://github.com/Aermoss/AerForge
Author: Yusuf Rencber
Author-email: yusufrencber546@gmail.com
License: MIT
Platform: UNKNOWN
License-File: LICENSE
